iso3166/__init__.py
iso3166/table.csv
iso_3166_1-0.0.3.dist-info/DESCRIPTION.rst
iso_3166_1-0.0.3.dist-info/METADATA
iso_3166_1-0.0.3.dist-info/metadata.json
iso_3166_1-0.0.3.dist-info/RECORD
iso_3166_1-0.0.3.dist-info/top_level.txt
iso_3166_1-0.0.3.dist-info/WHEEL
