Metadata-Version: 2.0
Name: iso-3166-1
Version: 0.0.3
Summary: ISO 3361-1 Country code package for Python
Home-page: http://github.com/spoqa/iso-3166-1
Author: Kang Hyojun
Author-email: ed@spoqa.com
License: Public Domain
Keywords: internationalization i18n country iso3166
Platform: UNKNOWN
Classifier: Development Status :: 1 - Planning
Classifier: Intended Audience :: Developers
Classifier: License :: Public Domain
Classifier: Operating System :: OS Independent
Classifier: Programming Language :: Python :: 2.5
Classifier: Programming Language :: Python :: 2.6
Classifier: Programming Language :: Python :: 2.7
Classifier: Programming Language :: Python :: 3.2
Classifier: Programming Language :: Python :: 3.3
Classifier: Programming Language :: Python :: 3.4
Classifier: Programming Language :: Python :: 3.5
Classifier: Programming Language :: Python :: Implementation :: CPython
Classifier: Programming Language :: Python :: Implementation :: PyPy
Classifier: Programming Language :: Python :: Implementation :: Stackless
Classifier: Topic :: Software Development :: Internationalization
Requires-Dist: setuptools
Requires-Dist: enum34; python_version=='2.5'
Requires-Dist: enum34; python_version=='2.6'
Requires-Dist: enum34; python_version=='2.7'
Requires-Dist: enum34; python_version=='3.2'
Requires-Dist: enum34; python_version=='3.3'
Provides-Extra: tests
Requires-Dist: pytest (>=2.7.0); extra == 'tests'
Requires-Dist: tox (>=2.1.1); extra == 'tests'
